odoo/addons/ssi_helpdesk_elearning/README.rst
odoo/addons/ssi_helpdesk_elearning/__init__.py
odoo/addons/ssi_helpdesk_elearning/__manifest__.py
odoo/addons/ssi_helpdesk_elearning/models/__init__.py
odoo/addons/ssi_helpdesk_elearning/models/helpdesk_ticket_resolution_documentation.py
odoo/addons/ssi_helpdesk_elearning/static/description/icon.png
odoo/addons/ssi_helpdesk_elearning/views/helpdesk_ticket_views.xml
odoo14_addon_ssi_helpdesk_elearning-14.0.3.1.0.dist-info/METADATA
odoo14_addon_ssi_helpdesk_elearning-14.0.3.1.0.dist-info/WHEEL
odoo14_addon_ssi_helpdesk_elearning-14.0.3.1.0.dist-info/top_level.txt
odoo14_addon_ssi_helpdesk_elearning-14.0.3.1.0.dist-info/RECORD
